main/__init__.py
main/divide.py
main/multiply.py
operators-1.0.1.dist-info/METADATA
operators-1.0.1.dist-info/WHEEL
operators-1.0.1.dist-info/top_level.txt
operators-1.0.1.dist-info/RECORD
