Metadata-Version: 2.1
Name: operators
Version: 1.0.1
Summary: Arithmetic Operators
Home-page: UNKNOWN
Author: Dushyant Lavania
Author-email: <dushyantlavania2001@gmail.com>
License: UNKNOWN
Keywords: python,Arithmetic operators
Platform: UNKNOWN
Classifier: Development Status :: 3 - Alpha
Classifier: Intended Audience :: Education
Classifier: Programming Language :: Python :: 2
Classifier: Programming Language :: Python :: 3
Classifier: Operating System :: MacOS :: MacOS X
Classifier: Operating System :: Microsoft :: Windows
